analytics_packages/__init__.py
analytics_packages/__main__.py
analytics_packages/custom_pandas.py
analytics_packages/custom_xlwings.py
kabbes_analytics_packages-0.5.0.dist-info/LICENSE
kabbes_analytics_packages-0.5.0.dist-info/METADATA
kabbes_analytics_packages-0.5.0.dist-info/WHEEL
kabbes_analytics_packages-0.5.0.dist-info/top_level.txt
kabbes_analytics_packages-0.5.0.dist-info/RECORD
