Metadata-Version: 2.1
Name: kabbes-analytics-packages
Version: 0.5.0
Summary: Helper functions for performing generic analysis
Home-page: https://pypi.org/project/kabbes-analytics-packages/
Author: James Kabbes
Author-email: james.kabbes@gmail.com
License: UNKNOWN
Project-URL: GitHub, https://github.com/jameskabbes/analytics_packages
Project-URL: Documentation, https://jameskabbes.github.io/analytics_packages
Platform: UNKNOWN
Classifier: Programming Language :: Python :: 3
Classifier: License :: OSI Approved :: MIT License
Classifier: Operating System :: OS Independent
Requires-Python: >=3.7
License-File: LICENSE
Requires-Dist: kabbes-dir-ops
Requires-Dist: pandas
Requires-Dist: matplotlib
Requires-Dist: numpy
Requires-Dist: xlwings
